codehash/__init__.py
codehash/codehash.py
pycodehash/__init__.py
pycodehash/codehash.py
naist_codehash-0.1.1.dist-info/LICENSE
naist_codehash-0.1.1.dist-info/METADATA
naist_codehash-0.1.1.dist-info/WHEEL
naist_codehash-0.1.1.dist-info/top_level.txt
naist_codehash-0.1.1.dist-info/RECORD
