Metadata-Version: 2.1
Name: naist-codehash
Version: 0.1.1
Summary: Support the use of CodeHash, a tool for measuring similarity between source code, from Python.
Home-page: https://github.com/pgDora56/pycodehash
Author: Kazuki F.
Author-email: doradora.prog@gmail.com
License: UNKNOWN
Platform: UNKNOWN
